[
  {
    "pack_code": "mighty_thor_by_rainy",
    "card_id": "202101a",
    "name": "Thor",
    "type": "hero",
    "octgn_id": "a9f65411-f86b-48a8-bcac-0564be021001",
    "pack_octgn_id": "a9f65411-f86b-48a8-bcac-0564be7f1ab9"
  },
  {
    "pack_code": "mighty_thor_by_rainy",
    "card_id": "202101b",
    "name": "Jane Foster",
    "type": "alter_ego",
    "octgn_id": "a9f65411-f86b-48a8-bcac-0564be021001",
    "pack_octgn_id": "a9f65411-f86b-48a8-bcac-0564be7f1ab9"
  },
  {
    "pack_code": "mighty_thor_by_rainy",
    "card_id": "202102",
    "name": "Roz Solomon",
    "type": "ally",
    "octgn_id": "a9f65411-f86b-48a8-bcac-0564be021002",
    "pack_octgn_id": "a9f65411-f86b-48a8-bcac-0564be7f1ab9"
  },
  {
    "pack_code": "mighty_thor_by_rainy",
    "card_id": "202103",
    "name": "Hammer Swing",
    "type": "event",
    "octgn_id": "a9f65411-f86b-48a8-bcac-0564be021003",
    "pack_octgn_id": "a9f65411-f86b-48a8-bcac-0564be7f1ab9"
  },
  {
    "pack_code": "mighty_thor_by_rainy",
    "card_id": "202104",
    "name": "Lightning Strike",
    "type": "event",
    "octgn_id": "a9f65411-f86b-48a8-bcac-0564be021004",
    "pack_octgn_id": "a9f65411-f86b-48a8-bcac-0564be7f1ab9"
  },
  {
    "pack_code": "mighty_thor_by_rainy",
    "card_id": "202105",
    "name": "Stand Fast",
    "type": "event",
    "octgn_id": "a9f65411-f86b-48a8-bcac-0564be021005",
    "pack_octgn_id": "a9f65411-f86b-48a8-bcac-0564be7f1ab9"
  },
  {
    "pack_code": "mighty_thor_by_rainy",
    "card_id": "202106",
    "name": "Congress of Worlds",
    "type": "support",
    "octgn_id": "a9f65411-f86b-48a8-bcac-0564be021006",
    "pack_octgn_id": "a9f65411-f86b-48a8-bcac-0564be7f1ab9"
  },
  {
    "pack_code": "mighty_thor_by_rainy",
    "card_id": "202107",
    "name": "Medical Clinic",
    "type": "support",
    "octgn_id": "a9f65411-f86b-48a8-bcac-0564be021007",
    "pack_octgn_id": "a9f65411-f86b-48a8-bcac-0564be7f1ab9"
  },
  {
    "pack_code": "mighty_thor_by_rainy",
    "card_id": "202108",
    "name": "Scrying Pool",
    "type": "support",
    "octgn_id": "a9f65411-f86b-48a8-bcac-0564be021008",
    "pack_octgn_id": "a9f65411-f86b-48a8-bcac-0564be7f1ab9"
  },
  {
    "pack_code": "mighty_thor_by_rainy",
    "card_id": "202109",
    "name": "Goddess of Thunder",
    "type": "upgrade",
    "octgn_id": "a9f65411-f86b-48a8-bcac-0564be021009",
    "pack_octgn_id": "a9f65411-f86b-48a8-bcac-0564be7f1ab9"
  },
  {
    "pack_code": "mighty_thor_by_rainy",
    "card_id": "202110",
    "name": "Mighty",
    "type": "upgrade",
    "octgn_id": "a9f65411-f86b-48a8-bcac-0564be021010",
    "pack_octgn_id": "a9f65411-f86b-48a8-bcac-0564be7f1ab9"
  },
  {
    "pack_code": "mighty_thor_by_rainy",
    "card_id": "202111",
    "name": "Mjolnir",
    "type": "upgrade",
    "octgn_id": "a9f65411-f86b-48a8-bcac-0564be021011",
    "pack_octgn_id": "a9f65411-f86b-48a8-bcac-0564be7f1ab9"
  },
  {
    "pack_code": "mighty_thor_by_rainy",
    "card_id": "202112",
    "name": "Unyielding",
    "type": "upgrade",
    "octgn_id": "a9f65411-f86b-48a8-bcac-0564be021012",
    "pack_octgn_id": "a9f65411-f86b-48a8-bcac-0564be7f1ab9"
  },
  {
    "pack_code": "mighty_thor_by_rainy",
    "card_id": "202113",
    "name": "Chemotherapy",
    "type": "obligation",
    "octgn_id": "a9f65411-f86b-48a8-bcac-0564be021013",
    "pack_octgn_id": "a9f65411-f86b-48a8-bcac-0564be7f1ab9"
  },
  {
    "pack_code": "mighty_thor_by_rainy",
    "card_id": "202114",
    "name": "War of the Realms",
    "type": "side_scheme",
    "octgn_id": "a9f65411-f86b-48a8-bcac-0564be021014",
    "pack_octgn_id": "a9f65411-f86b-48a8-bcac-0564be7f1ab9"
  },
  {
    "pack_code": "mighty_thor_by_rainy",
    "card_id": "202115",
    "name": "Malekith",
    "type": "minion",
    "octgn_id": "a9f65411-f86b-48a8-bcac-0564be021015",
    "pack_octgn_id": "a9f65411-f86b-48a8-bcac-0564be7f1ab9"
  },
  {
    "pack_code": "mighty_thor_by_rainy",
    "card_id": "202116",
    "name": "War Witches",
    "type": "minion",
    "octgn_id": "a9f65411-f86b-48a8-bcac-0564be021016",
    "pack_octgn_id": "a9f65411-f86b-48a8-bcac-0564be7f1ab9"
  },
  {
    "pack_code": "mighty_thor_by_rainy",
    "card_id": "202117",
    "name": "Execute",
    "type": "treachery",
    "octgn_id": "a9f65411-f86b-48a8-bcac-0564be021017",
    "pack_octgn_id": "a9f65411-f86b-48a8-bcac-0564be7f1ab9"
  },
  {
    "pack_code": "mighty_thor_by_rainy",
    "card_id": "202118",
    "name": "Hostile Takeover",
    "type": "treachery",
    "octgn_id": "a9f65411-f86b-48a8-bcac-0564be021018",
    "pack_octgn_id": "a9f65411-f86b-48a8-bcac-0564be7f1ab9"
  }
]